{"stats":{"minecraft:crafted":{"minecraft:wooden_sword":3,"minecraft:stick":8,"biomesoplenty:mahogany_planks":36,"minecraft:wooden_pickaxe":1,"minecraft:wooden_axe":1},"minecraft:mined":{"minecraft:grass":5,"biomesoplenty:mahogany_leaves":5,"minecraft:melon":10,"biomesoplenty:watergrass":3,"farmersdelight:wild_rice":2,"biomesoplenty:mahogany_log":20,"minecraft:lily_pad":2,"minecraft:fern":5,"biomesoplenty:waterlily":15},"minecraft:custom":{"minecraft:open_barrel":1,"minecraft:time_since_rest":25941,"minecraft:play_time":25941,"minecraft:sprint_one_cm":30139,"minecraft:damage_taken":106,"minecraft:walk_one_cm":47805,"minecraft:sneak_time":57,"minecraft:walk_under_water_one_cm":3201,"minecraft:drop":6,"minecraft:jump":385,"minecraft:damage_dealt":48,"minecraft:time_since_death":25941,"minecraft:walk_on_water_one_cm":32635,"minecraft:total_world_time":25941,"minecraft:interact_with_crafting_table":3,"minecraft:swim_one_cm":7959,"minecraft:fly_one_cm":47220,"minecraft:fall_one_cm":5657},"minecraft:dropped":{"alexsmobs:animal_dictionary":2,"minecraft:cod":2,"minecraft:cooked_cod":2},"minecraft:used":{"minecraft:wooden_axe":5,"biomesoplenty:mahogany_log":4,"minecraft:wooden_sword":9,"minecraft:melon_slice":11,"minecraft:wooden_pickaxe":6},"minecraft:picked_up":{"farmersdelight:rice":3,"biomesoplenty:waterlily":15,"biomesoplenty:mahogany_log":20,"minecraft:cooked_cod":4,"minecraft:lily_pad":1,"minecraft:melon_slice":53,"minecraft:cod":2,"alexsmobs:animal_dictionary":1}},"DataVersion":3465}